{
  "generated_at": "2026-01-02T21:53:47.117970Z",
  "atom_version": "v1",
  "chunk_seconds": 5,
  "overlap_seconds": 1,
  "videos": {
    "10065395-hd_1080_1920_30fps": {
      "atom_count": 1
    },
    "12215302_1920_1080_30fps": {
      "atom_count": 1
    },
    "12317106_1080_1920_60fps": {
      "atom_count": 1
    },
    "12335641_2160_3840_30fps": {
      "atom_count": 1
    },
    "12778543_3840_2160_24fps": {
      "atom_count": 1
    },
    "12959204_2160_3840_30fps": {
      "atom_count": 1
    },
    "13528209_3840_2160_25fps": {
      "atom_count": 1
    },
    "13654077_3840_2160_30fps": {
      "atom_count": 1
    },
    "14619009_3840_2160_30fps": {
      "atom_count": 1
    },
    "14726757_2160_3840_30fps": {
      "atom_count": 1
    },
    "14825026_2160_3840_30fps": {
      "atom_count": 1
    },
    "14827816_1080_1920_30fps": {
      "atom_count": 1
    },
    "14833150_1080_1920_60fps": {
      "atom_count": 1
    },
    "14845631_3840_2160_30fps": {
      "atom_count": 1
    },
    "14846808_2160_3840_30fps": {
      "atom_count": 1
    },
    "14851369_1920_1080_30fps": {
      "atom_count": 1
    },
    "14852154_1080_1922_60fps": {
      "atom_count": 1
    }
  },
  "summary": {
    "videos_with_atoms": 17,
    "total_atoms": 17
  }
}